[{"pid": "2330972", "date": "28/07/2021", "time": "02:15 PM", "court_type": "Court of Appeal", "division": "Civil Division", "judicial_officer": "Justice Kyrou, Justice Kennedy, Justice Walker", "case_number": "S EAPCI 2020 0042", "description": "David Charles Quin (in his capacity as liquidator of Roderick Group Pty Ltd (In Liquidation) (ACN 127 974 761)) & Ors. v. David William Vlahos", "court_address": "Via Email", "summary": "For Judgment - Leave to Appeal", "maps_url": ""}, {"pid": "2330973", "date": "28/07/2021", "time": "02:15 PM", "court_type": "Court of Appeal", "division": "Civil Division", "judicial_officer": "Justice Kyrou, Justice Kennedy, Justice Walker", "case_number": "S EAPCI 2020 0042", "description": "David Charles Quin (in his capacity as liquidator of Roderick Group Pty Ltd (In Liquidation) (ACN 127 974 761)) & Ors. v. David William Vlahos", "court_address": "Via Email", "summary": "Judgment", "maps_url": ""}, {"pid": "2330974", "date": "28/07/2021", "time": "11:00 AM", "court_type": "Trial Division", "division": "Criminal Division", "judicial_officer": "Justice Croucher", "case_number": "S CR 2002 1450", "description": "R v. T H R", "court_address": "In Chambers", "summary": "Major Review under s35 of Crimes (MIUT) Act 1997 (Virtual Hearing)", "maps_url": ""}, {"pid": "2330975", "date": "28/07/2021", "time": "10:15 AM", "court_type": "Trial Division", "division": "Criminal Division", "judicial_officer": "Justice Jane Dixon", "case_number": "S ECR 2021 0184", "description": "In the matter of an application by Nhat Hai LE", "court_address": "In Chambers", "summary": "Application for Bail (Virtual Hearing)", "maps_url": ""}, {"pid": "2330976", "date": "28/07/2021", "time": "02:15 PM", "court_type": "Trial Division", "division": "Criminal Division", "judicial_officer": "Justice Champion", "case_number": "S ECR 2021 0170", "description": "In the matter of an application by Jovan KUDRIC", "court_address": "In Chambers", "summary": "For Judgment (Virtual Hearing)", "maps_url": ""}, {"pid": "2330977", "date": "28/07/2021", "time": "10:00 AM", "court_type": "Trial Division", "division": "Criminal Division", "judicial_officer": "Justice Taylor", "case_number": "S ECR 2021 0058", "description": "R v. K V", "court_address": "In Chambers", "summary": "Examination - s198B of the Criminal Procedure Act 2009 (Virtual Hearing)", "maps_url": ""}, {"pid": "2330978", "date": "28/07/2021", "time": "10:00 AM", "court_type": "Trial Division", "division": "Criminal Division", "judicial_officer": "Justice Taylor", "case_number": "S ECR 2021 0066", "description": "R v. Hudson MARTIN", "court_address": "In Chambers", "summary": "Examination - s198B of the Criminal Procedure Act 2009 (Virtual Hearing)", "maps_url": ""}, {"pid": "2330979", "date": "28/07/2021", "time": "10:00 AM", "court_type": "Trial Division", "division": "Criminal Division", "judicial_officer": "Justice Coghlan", "case_number": "S ECR 2019 0264", "description": "R v. Mark DIXON", "court_address": "Court 12, Ground Floor 210 William Street, Melb.", "summary": "Part Heard", "maps_url": "https://maps.supremecourt.vic.gov.au/poi/964014"}, {"pid": "2330980", "date": "28/07/2021", "time": "10:00 AM", "court_type": "Trial Division", "division": "Criminal Division", "judicial_officer": "Justice Coghlan", "case_number": "S ECR 2019 0265", "description": "R v. Jack HARVEY", "court_address": "Court 12, Ground Floor 210 William Street, Melb.", "summary": "Part Heard", "maps_url": "https://maps.supremecourt.vic.gov.au/poi/964014"}, {"pid": "2330981", "date": "28/07/2021", "time": "10:00 AM", "court_type": "Trial Division", "division": "Criminal Division", "judicial_officer": "Justice Coghlan", "case_number": "S ECR 2019 0266", "description": "R v. Stephen TAHANEY", "court_address": "Court 12, Ground Floor 210 William Street, Melb.", "summary": "Part Heard", "maps_url": "https://maps.supremecourt.vic.gov.au/poi/964014"}, {"pid": "2330982", "date": "28/07/2021", "time": "09:30 AM", "court_type": "Trial Division", "division": "Criminal Division", "judicial_officer": "Justice Coghlan", "case_number": "S CR 2017 0173", "description": "R v. George MARROGI", "court_address": "In Chambers", "summary": "For Mention (Virtual Hearing)", "maps_url": ""}, {"pid": "2330983", "date": "28/07/2021", "time": "09:00 AM", "court_type": "Trial Division", "division": "Criminal Division", "judicial_officer": "Judicial Registrar Freeman", "case_number": "S ECR 2021 0188", "description": "R v. Simiona TUTERU", "court_address": "In Chambers", "summary": "Post Committal Directions (Virtual Hearing)", "maps_url": ""}, {"pid": "2330984", "date": "28/07/2021", "time": "09:30 AM", "court_type": "Trial Division", "division": "Criminal Division", "judicial_officer": "Judicial Registrar Freeman", "case_number": "S ECR 2021 0183", "description": "R v. Evander WILSON", "court_address": "In Chambers", "summary": "Post Committal Directions (Virtual Hearing)", "maps_url": ""}, {"pid": "2330985", "date": "28/07/2021", "time": "02:15 PM", "court_type": "Trial Division", "division": "Common Law Division", "judicial_officer": "Justice McMillan", "case_number": "S ECI 2021 02580", "description": "Knight 34 Langdon Road Pty Ltd (ACN 613 271 079) v. Tick Box Property Pty Ltd (ACN 159 925 658) & Ors. ", "court_address": "In Chambers", "summary": "Application (Virtual Hearing)", "maps_url": ""}, {"pid": "2330986", "date": "28/07/2021", "time": "10:30 AM", "court_type": "Trial Division", "division": "Common Law Division", "judicial_officer": "Justice Moore", "case_number": "S CI 2016 01472", "description": "Gerard Hards Maher v. Christine Burden (as an Executor of the Will of Maureen Brown, deceased) & Ors. ", "court_address": "Court 2, Ground Floor, Old High Court 450 Little Bourke Street, Melb.", "summary": "Trial (Virtual Hearing)", "maps_url": "https://maps.supremecourt.vic.gov.au/poi/964483"}, {"pid": "2330987", "date": "28/07/2021", "time": "10:30 AM", "court_type": "Trial Division", "division": "Common Law Division", "judicial_officer": "Justice Moore", "case_number": "S CI 2016 01961", "description": "Thomas Celestine Maher & Ors. v. Christine Burden (as Executor of the Will of Maureen Brown, deceased) & Ors. ", "court_address": "Court 2, Ground Floor, Old High Court 450 Little Bourke Street, Melb.", "summary": "Trial (Virtual Hearing)", "maps_url": "https://maps.supremecourt.vic.gov.au/poi/964483"}, {"pid": "2330988", "date": "28/07/2021", "time": "10:30 AM", "court_type": "Trial Division", "division": "Common Law Division", "judicial_officer": "Justice Moore", "case_number": "S ECI 2019 04596", "description": "David John Maher v. Nathan Kuperholz (as Administrator of the Will annexed of the Estate of Thomas Patrick Maher, deceased)", "court_address": "Court 2, Ground Floor, Old High Court 450 Little Bourke Street, Melb.", "summary": "Trial (Virtual Hearing)", "maps_url": "https://maps.supremecourt.vic.gov.au/poi/964483"}, {"pid": "2330989", "date": "28/07/2021", "time": "10:00 AM", "court_type": "Trial Division", "division": "Common Law Division", "judicial_officer": "Justice Gorton", "case_number": "S ECI 2018 02370", "description": "Anthony James Sheridan & Ors. v. Australian Pacific Airports (Melbourne) Pty Ltd (ACN 076 999 114)", "court_address": "In Chambers", "summary": "For Judgment (Virtual Hearing)", "maps_url": ""}, {"pid": "2330990", "date": "28/07/2021", "time": "10:30 AM", "court_type": "Trial Division", "division": "Common Law Division", "judicial_officer": "Justice J Forrest", "case_number": "S ECI 2020 01541", "description": "DP (a pseudonym) v. Bishop Paul Bernard Bird", "court_address": "In Chambers", "summary": "Trial (Virtual Hearing)", "maps_url": ""}, {"pid": "2330991", "date": "28/07/2021", "time": "10:30 AM", "court_type": "Trial Division", "division": "Commercial Court", "judicial_officer": "Justice Connock", "case_number": "S ECI 2021 02618", "description": "Emergent Solutions Pty Ltd (ACN 607 054 302) & Ors. v. Penguin Random House Australia Pty Ltd (ACN 004 815 703)", "court_address": "In Chambers", "summary": "For Mention (Virtual Hearing)", "maps_url": ""}, {"pid": "2330992", "date": "28/07/2021", "time": "02:15 PM", "court_type": "Trial Division", "division": "Commercial Court", "judicial_officer": "Justice Osborne", "case_number": "S ECI 2021 01479", "description": "In the Matter of Grand Land Property Pty Ltd (ACN 613 539 601), Aurum Estate Pty Ltd (ACN 614 427 342), Mt Albert Development Pty Ltd (ACN 611 497 735), Grand Land Greenwich Pty Ltd (ACN 624 095 647) and Grand Land Estate Pty Ltd (ACN 621 292 233)", "court_address": "In Chambers", "summary": "Application (Virtual Hearing)", "maps_url": ""}, {"pid": "2330993", "date": "28/07/2021", "time": "10:30 AM", "court_type": "Trial Division", "division": "Commercial Court", "judicial_officer": "Associate Justice Hetyey", "case_number": "S ECI 2021 02616", "description": "In the Matter of Gold Road No.2 Pty Ltd (Receiver & Manager appointed) (Administrator Appointed) (ACN 608 874 273)", "court_address": "In Chambers", "summary": "For Mention (Virtual Hearing)", "maps_url": ""}, {"pid": "2330994", "date": "28/07/2021", "time": "10:30 AM", "court_type": "Trial Division", "division": "Commercial Court", "judicial_officer": "Associate Justice Hetyey", "case_number": "S ECI 2021 02380", "description": "In the Matter of Sceam Construction (ACN 141 136 816)", "court_address": "On the Papers", "summary": "Company Application not for Winding Up", "maps_url": ""}, {"pid": "2330995", "date": "28/07/2021", "time": "10:30 AM", "court_type": "Trial Division", "division": "Commercial Court", "judicial_officer": "Associate Justice Hetyey", "case_number": "S ECI 2021 02468", "description": "In the Matter of Syncordia Group Operations Pty Ltd (ACN 151 557 676)", "court_address": "On the Papers", "summary": "Company Application not for Winding Up", "maps_url": ""}, {"pid": "2330996", "date": "28/07/2021", "time": "02:15 PM", "court_type": "Trial Division", "division": "Commercial Court", "judicial_officer": "Associate Justice Irving", "case_number": "S ECI 2021 01890", "description": "In the Matter of Idevelopment Group Pty Ltd (ACN 134 745 716)", "court_address": "In Chambers", "summary": " (Virtual Hearing)", "maps_url": ""}, {"pid": "2330997", "date": "28/07/2021", "time": "02:15 PM", "court_type": "Trial Division", "division": "Commercial Court", "judicial_officer": "Associate Justice Irving", "case_number": "S ECI 2021 01931", "description": "In the Matter of Carina Colour Pty Ltd (ACN 133 686 889)", "court_address": "In Chambers", "summary": " (Virtual Hearing)", "maps_url": ""}, {"pid": "2330998", "date": "28/07/2021", "time": "02:15 PM", "court_type": "Trial Division", "division": "Commercial Court", "judicial_officer": "Associate Justice Irving", "case_number": "S ECI 2021 02096", "description": "In the Matter of Macquarie Patient Transport Pty Ltd ACN 610 121 732", "court_address": "In Chambers", "summary": " (Virtual Hearing)", "maps_url": ""}, {"pid": "2330999", "date": "28/07/2021", "time": "02:15 PM", "court_type": "Trial Division", "division": "Commercial Court", "judicial_officer": "Associate Justice Irving", "case_number": "S ECI 2021 02205", "description": "In the Matter of Top Sheen Painting Pty Ltd ACN 613 241 482", "court_address": "In Chambers", "summary": " (Virtual Hearing)", "maps_url": ""}, {"pid": "2331000", "date": "28/07/2021", "time": "02:15 PM", "court_type": "Trial Division", "division": "Commercial Court", "judicial_officer": "Associate Justice Irving", "case_number": "S ECI 2021 02206", "description": "In the Matter of Top Sheen Group Pty Ltd ACN 624 585 646", "court_address": "In Chambers", "summary": " (Virtual Hearing)", "maps_url": ""}, {"pid": "2331001", "date": "28/07/2021", "time": "02:15 PM", "court_type": "Trial Division", "division": "Commercial Court", "judicial_officer": "Associate Justice Irving", "case_number": "S ECI 2021 02207", "description": "In the Matter of AB Studio Pty Ltd (ACN 086 107 299)", "court_address": "In Chambers", "summary": " (Virtual Hearing)", "maps_url": ""}, {"pid": "2331002", "date": "28/07/2021", "time": "02:15 PM", "court_type": "Trial Division", "division": "Commercial Court", "judicial_officer": "Associate Justice Irving", "case_number": "S ECI 2021 02227", "description": "In the Matter of Ikkon Pty Ltd (ACN 096 481 480)", "court_address": "In Chambers", "summary": " (Virtual Hearing)", "maps_url": ""}, {"pid": "2331003", "date": "28/07/2021", "time": "02:15 PM", "court_type": "Trial Division", "division": "Commercial Court", "judicial_officer": "Associate Justice Irving", "case_number": "S ECI 2021 02246", "description": "In the Matter of Taxon Trading Pty Ltd (ACN 609 208 746)", "court_address": "In Chambers", "summary": " (Virtual Hearing)", "maps_url": ""}, {"pid": "2331004", "date": "28/07/2021", "time": "02:15 PM", "court_type": "Trial Division", "division": "Commercial Court", "judicial_officer": "Associate Justice Irving", "case_number": "S ECI 2021 02260", "description": "In the Matter of Walkalong Travel Shoe and Sporting Goods Repairs Pty Ltd (ACN 602 183 853)", "court_address": "In Chambers", "summary": " (Virtual Hearing)", "maps_url": ""}, {"pid": "2331005", "date": "28/07/2021", "time": "02:15 PM", "court_type": "Trial Division", "division": "Commercial Court", "judicial_officer": "Associate Justice Irving", "case_number": "S ECI 2021 02263", "description": "In the Matter of Southern Cross Engineering (Aust) Pty Ltd (ACN 095 865 464)", "court_address": "In Chambers", "summary": " (Virtual Hearing)", "maps_url": ""}, {"pid": "2331006", "date": "28/07/2021", "time": "02:15 PM", "court_type": "Trial Division", "division": "Commercial Court", "judicial_officer": "Associate Justice Irving", "case_number": "S ECI 2021 02287", "description": "In the Matter of AJ & SS Investments Pty Ltd  (ACN 166 405 063)", "court_address": "In Chambers", "summary": " (Virtual Hearing)", "maps_url": ""}, {"pid": "2331007", "date": "28/07/2021", "time": "02:15 PM", "court_type": "Trial Division", "division": "Commercial Court", "judicial_officer": "Associate Justice Irving", "case_number": "S ECI 2021 02297", "description": "In the Matter of Gihl Investments Pty Ltd (ACN 633 362 302)", "court_address": "In Chambers", "summary": " (Virtual Hearing)", "maps_url": ""}, {"pid": "2331008", "date": "28/07/2021", "time": "10:30 AM", "court_type": "Trial Division", "division": "Commercial Court", "judicial_officer": "Judicial Registrar Woronczak", "case_number": "S ECI 2021 02195", "description": "In the Matter of GT Construction Group Pty Ltd (ACN 157 812 836)", "court_address": "In Chambers", "summary": " (Virtual Hearing)", "maps_url": ""}, {"pid": "2331009", "date": "28/07/2021", "time": "10:30 AM", "court_type": "Trial Division", "division": "Commercial Court", "judicial_officer": "Judicial Registrar Woronczak", "case_number": "S ECI 2021 02209", "description": "In the Matter of Southern Cross School Photos Pty Ltd (ACN 071 147 987)", "court_address": "In Chambers", "summary": " (Virtual Hearing)", "maps_url": ""}, {"pid": "2331010", "date": "28/07/2021", "time": "10:30 AM", "court_type": "Trial Division", "division": "Commercial Court", "judicial_officer": "Judicial Registrar Woronczak", "case_number": "S ECI 2021 02215", "description": "In the Matter of Bai Fu Xin Pty Ltd (ACN 616 118 579)", "court_address": "In Chambers", "summary": " (Virtual Hearing)", "maps_url": ""}, {"pid": "2331011", "date": "28/07/2021", "time": "10:30 AM", "court_type": "Trial Division", "division": "Commercial Court", "judicial_officer": "Judicial Registrar Woronczak", "case_number": "S ECI 2021 02218", "description": "In the Matter of Xin Hai City (Forrest Hill) Pty Ltd (ACN 623 880 062)", "court_address": "In Chambers", "summary": " (Virtual Hearing)", "maps_url": ""}, {"pid": "2331012", "date": "28/07/2021", "time": "10:30 AM", "court_type": "Trial Division", "division": "Commercial Court", "judicial_officer": "Judicial Registrar Woronczak", "case_number": "S ECI 2021 02228", "description": "In the Matter of Bowman Investments (Qld) Pty Ltd (ACN 153 117 643)", "court_address": "In Chambers", "summary": " (Virtual Hearing)", "maps_url": ""}, {"pid": "2331013", "date": "28/07/2021", "time": "10:30 AM", "court_type": "Trial Division", "division": "Commercial Court", "judicial_officer": "Judicial Registrar Woronczak", "case_number": "S ECI 2021 02288", "description": "In the Matter of Justway Enterprises Pty Ltd (ACN 645 446 939) Trading as Local Orders Wholesale Direct Food Services", "court_address": "In Chambers", "summary": " (Virtual Hearing)", "maps_url": ""}, {"pid": "2331014", "date": "28/07/2021", "time": "10:30 AM", "court_type": "Trial Division", "division": "Commercial Court", "judicial_officer": "Judicial Registrar Woronczak", "case_number": "S ECI 2021 02298", "description": "In the Matter of Sal Logistics Pty Ltd (ACN 626 041 905)", "court_address": "In Chambers", "summary": " (Virtual Hearing)", "maps_url": ""}, {"pid": "2331015", "date": "28/07/2021", "time": "11:00 AM", "court_type": "Trial Division", "division": "Commercial Court", "judicial_officer": "Judicial Registrar Woronczak", "case_number": "S ECI 2021 01487", "description": "In the Matter of Fresh Franchising Australia (FFA) Pty Ltd (ACN 612 172 282)", "court_address": "In Chambers", "summary": " (Virtual Hearing)", "maps_url": ""}, {"pid": "2331016", "date": "28/07/2021", "time": "11:00 AM", "court_type": "Trial Division", "division": "Commercial Court", "judicial_officer": "Judicial Registrar Woronczak", "case_number": "S ECI 2021 02010", "description": "In the Matter of JDR Property Developers Pty Ltd (ACN 168 443 525)", "court_address": "In Chambers", "summary": " (Virtual Hearing)", "maps_url": ""}, {"pid": "2331017", "date": "28/07/2021", "time": "11:00 AM", "court_type": "Trial Division", "division": "Commercial Court", "judicial_officer": "Judicial Registrar Woronczak", "case_number": "S ECI 2021 02285", "description": "In the Matter of All J's Property Investments Pty Ltd (ACN 138 935 967)", "court_address": "In Chambers", "summary": " (Virtual Hearing)", "maps_url": ""}, {"pid": "2331018", "date": "28/07/2021", "time": "11:30 AM", "court_type": "Trial Division", "division": "Commercial Court", "judicial_officer": "Judicial Registrar Woronczak", "case_number": "S ECI 2021 01803", "description": "In the Matter of Quantum Industries Pty Ltd (ACN 612 363 961)", "court_address": "In Chambers", "summary": " (Virtual Hearing)", "maps_url": ""}, {"pid": "2331019", "date": "28/07/2021", "time": "11:30 AM", "court_type": "Trial Division", "division": "Commercial Court", "judicial_officer": "Judicial Registrar Woronczak", "case_number": "S ECI 2021 02152", "description": "In the Matter of Global Steel Solutions Pty Ltd (ACN 636 764 522)", "court_address": "In Chambers", "summary": " (Virtual Hearing)", "maps_url": ""}, {"pid": "2331020", "date": "28/07/2021", "time": "10:30 AM", "court_type": "Trial Division", "division": "Associate Judges", "judicial_officer": "Associate Justice Efthim", "case_number": "S ECI 2020 02382", "description": "MC SOF XXXV Pty Ltd (ACN 628 979 448) v. Ming Lu & Ors. ", "court_address": "In Chambers", "summary": "Application for Substituted Service (Virtual Hearing)", "maps_url": ""}, {"pid": "2331021", "date": "28/07/2021", "time": "10:30 AM", "court_type": "Trial Division", "division": "Associate Judges", "judicial_officer": "Associate Justice Efthim", "case_number": "S ECI 2021 01652", "description": "Andre McKechnie v. Secretary of the Department of Justice & Ors. ", "court_address": "In Chambers", "summary": "Application (Virtual Hearing)", "maps_url": ""}, {"pid": "2331022", "date": "28/07/2021", "time": "02:00 PM", "court_type": "Trial Division", "division": "Pre-Trial Conferences", "judicial_officer": "Deputy Prothonotary Valladares", "case_number": "S ECI 2021 00331", "description": "Brian Stafford v. Amaca Pty Limited (formerly known as James Hardie & Co Pty Ltd)", "court_address": "In Chambers", "summary": "Pre-Trial Conference (Virtual Hearing)", "maps_url": ""}, {"pid": "2331023", "date": "28/07/2021", "time": "10:00 AM", "court_type": "Trial Division", "division": "Pre-Trial Conferences", "judicial_officer": "Deputy Prothonotary Konstantopoulos", "case_number": "S ECI 2021 01069", "description": "Peter Gilbert Pallot v. Amaca Pty Ltd (under NSW administered winding up)", "court_address": "In Chambers", "summary": "Pre-Trial Conference (Virtual Hearing)", "maps_url": ""}]